README.rst
setup.cfg
setup.py
obdlib/__init__.py
obdlib/elm327.py
obdlib/logging.py
obdlib/response.py
obdlib/scanner.py
obdlib/uart.py
obdlib/utils.py
obdlib.egg-info/PKG-INFO
obdlib.egg-info/SOURCES.txt
obdlib.egg-info/dependency_links.txt
obdlib.egg-info/not-zip-safe
obdlib.egg-info/requires.txt
obdlib.egg-info/top_level.txt
obdlib/obd/__init__.py
obdlib/obd/commands.py
obdlib/obd/modes.py
obdlib/obd/pids.py
obdlib/obd/sensors.py
obdlib/obd/protocols/__init__.py
obdlib/obd/protocols/base.py
obdlib/obd/protocols/can_protocols.py
obdlib/obd/protocols/protocols.py